digitalassistantcontext/__init__.py
digitalassistantcontext/context.py
digital_assistant_context-0.0.4.dist-info/METADATA
digital_assistant_context-0.0.4.dist-info/WHEEL
digital_assistant_context-0.0.4.dist-info/top_level.txt
digital_assistant_context-0.0.4.dist-info/RECORD
