Metadata-Version: 2.1
Name: digital-assistant-context
Version: 0.0.4
Summary: Managing context as a set of variables for executing a digital assistant script
Author: Aleksandr Belov
Author-email: a.belov@asbelon.ru
Keywords: digital assistant
Classifier: Development Status :: 1 - Planning
Classifier: Intended Audience :: Developers
Classifier: Programming Language :: Python :: 3
Classifier: Operating System :: MacOS :: MacOS X
Classifier: Operating System :: Microsoft :: Windows
